Metadata-Version: 1.0
Name: bpg
Version: 1.1
Summary: template engine with expression
Home-page: http://era.nutanix.com
Author: nobody
Author-email: era@nutanix.com
License: Apache 2.0
Platform: UNKNOWN
